yoomoney/__init__.py
yoomoney/client.py
yoomoney/exceptions.py
yoomoney/account/__init__.py
yoomoney/account/account.py
yoomoney/account/balance_details.py
yoomoney/account/card.py
yoomoney/authorize/__init__.py
yoomoney/authorize/authorize.py
yoomoney/history/__init__.py
yoomoney/history/history.py
yoomoney/operation/__init__.py
yoomoney/operation/operation.py
yoomoney/operation_details/__init__.py
yoomoney/operation_details/digital_bonus.py
yoomoney/operation_details/digital_good.py
yoomoney/operation_details/digital_product.py
yoomoney/operation_details/operation_details.py
yoomoney/quickpay/__init__.py
yoomoney/quickpay/quickpay.py
YooMoney-0.1.0.dist-info/LICENSE
YooMoney-0.1.0.dist-info/METADATA
YooMoney-0.1.0.dist-info/WHEEL
YooMoney-0.1.0.dist-info/top_level.txt
YooMoney-0.1.0.dist-info/RECORD
