Metadata-Version: 1.0
Name: YooMoney
Version: 0.1.0
Summary: Unofficial YooMoney API python library
Home-page: https://github.com/AlekseyKorshuk/yoomoney-api
Author: AlekseyKorshuk
Author-email: ale-kor02@mail.ru
License: GPL-3.0
Platform: UNKNOWN
